MANIFEST.in
README.rst
setup.py
drf_otp_permissions/__init__.py
drf_otp_permissions/encryptions.py
drf_otp_permissions/headers.py
drf_otp_permissions/otp.py
drf_otp_permissions/permissions.py
drf_otp_permissions.egg-info/PKG-INFO
drf_otp_permissions.egg-info/SOURCES.txt
drf_otp_permissions.egg-info/dependency_links.txt
drf_otp_permissions.egg-info/not-zip-safe
drf_otp_permissions.egg-info/requires.txt
drf_otp_permissions.egg-info/top_level.txt