Metadata-Version: 1.0
Name: drf-otp-permissions
Version: 0.4.2
Summary: OTP permissions for Django REST Framework
Home-page: https://gitlab.com/taelimoh/drf-otp-permissions
Author: Tae-lim Oh
Author-email: taelimoh@gmail.com
License: MIT
Keywords: django rest framework drf otp permission
Platform: UNKNOWN
